README.md
setup.py
planks/__init__.py
planks.egg-info/PKG-INFO
planks.egg-info/SOURCES.txt
planks.egg-info/dependency_links.txt
planks.egg-info/top_level.txt